trcks-0.4.2.dist-info/METADATA
trcks-0.4.2.dist-info/WHEEL
trcks-0.4.2.dist-info/entry_points.txt
trcks-0.4.2.dist-info/licenses/LICENSE
trcks/__init__.py
trcks/_typing.py
trcks/fp/__init__.py
trcks/fp/composition.py
trcks/fp/monads/__init__.py
trcks/fp/monads/awaitable.py
trcks/fp/monads/awaitable_result.py
trcks/fp/monads/identity.py
trcks/fp/monads/result.py
trcks/oop.py
trcks/py.typed
trcks-0.4.2.dist-info/RECORD
