Metadata-Version: 2.4
Name: trcks
Version: 0.4.2
Summary: Type-safe railway-oriented programming (ROP)
Keywords: composition,control flow,error handling,fp,functional programming,monad,object-oriented programming,oop,pipeline,railway-oriented programming,result type,rop,static typing,type safety
Author: Christoph Gietl
Maintainer: Christoph Gietl
License-Expression: MIT
License-File: LICENSE
Classifier: Development Status :: 3 - Alpha
Classifier: Intended Audience :: Developers
Classifier: Operating System :: OS Independent
Classifier: Programming Language :: Python
Classifier: Programming Language :: Python :: 3
Classifier: Programming Language :: Python :: 3 :: Only
Classifier: Programming Language :: Python :: 3.10
Classifier: Programming Language :: Python :: 3.11
Classifier: Programming Language :: Python :: 3.12
Classifier: Programming Language :: Python :: 3.13
Classifier: Programming Language :: Python :: 3.14
Classifier: Topic :: Software Development :: Libraries :: Python Modules
Classifier: Typing :: Typed
Project-URL: Documentation, https://christophgietl.github.io/trcks/
Project-URL: Issues, https://github.com/christophgietl/trcks/issues
Project-URL: Repository, https://github.com/christophgietl/trcks.git
Requires-Python: >=3.10
Requires-Dist: typing-extensions>=4.12; python_full_version < "3.13"
Provides-Extra: mypy
Requires-Dist: mypy>=1.16; extra == "mypy"
Provides-Extra: pyright
Requires-Dist: pyright>=1.1.391; extra == "pyright"
Requires-Dist: pyright>=1.1.407; python_full_version >= "3.14" and extra == "pyright"
